chinapharm/__init__.py
chinapharm/core.py
chinapharm-0.0.1a1.dist-info/licenses/LICENSE
chinapharm-0.0.1a1.dist-info/METADATA
chinapharm-0.0.1a1.dist-info/WHEEL
chinapharm-0.0.1a1.dist-info/top_level.txt
chinapharm-0.0.1a1.dist-info/RECORD
