Metadata-Version: 2.4
Name: chinapharm
Version: 0.0.1a1
Summary: China pharmaceutical industry toolkit
Home-page: https://github.com/chinapharm/chinapharm
Author: ChinaPharm Team
Author-email: ChinaPharm Team <team@chinapharm.org>
Maintainer-email: ChinaPharm Team <team@chinapharm.org>
License: MIT
Project-URL: Homepage, https://github.com/chinapharm/chinapharm
Project-URL: Repository, https://github.com/chinapharm/chinapharm
Project-URL: Documentation, https://github.com/chinapharm/chinapharm#readme
Project-URL: Issues, https://github.com/chinapharm/chinapharm/issues
Keywords: pharmaceutical,china,industry,toolkit
Classifier: Development Status :: 3 - Alpha
Classifier: Intended Audience :: Developers
Classifier: License :: OSI Approved :: MIT License
Classifier: Programming Language :: Python :: 3
Classifier: Programming Language :: Python :: 3.7
Classifier: Programming Language :: Python :: 3.8
Classifier: Programming Language :: Python :: 3.9
Classifier: Programming Language :: Python :: 3.10
Classifier: Programming Language :: Python :: 3.11
Requires-Python: >=3.7
License-File: LICENSE
Requires-Dist: numpy>=1.19.0
Requires-Dist: pandas>=1.3.0
Dynamic: author
Dynamic: home-page
Dynamic: license-file
Dynamic: requires-python
